{
"meta":{"test_sets":["test"],"test_metrics":[{"best_value":"Min","name":"RMSE"}],"learn_metrics":[{"best_value":"Min","name":"RMSE"}],"launch_mode":"Train","parameters":"","iteration_count":1000,"learn_sets":["learn"],"name":"experiment"},
"iterations":[
{"learn":[47.90315654],"iteration":0,"passed_time":5.509953048,"remaining_time":5504.443095,"test":[47.81746604]},
{"learn":[47.8208957],"iteration":1,"passed_time":9.536015605,"remaining_time":4758.471787,"test":[47.734725]},
{"learn":[47.74305037],"iteration":2,"passed_time":12.49745066,"remaining_time":4153.319437,"test":[47.65620584]},
{"learn":[47.67464624],"iteration":3,"passed_time":14.87570748,"remaining_time":3704.051161,"test":[47.58750713]},
{"learn":[47.61196183],"iteration":4,"passed_time":17.57443994,"remaining_time":3497.313549,"test":[47.52413982]},
{"learn":[47.5530339],"iteration":5,"passed_time":20.04177762,"remaining_time":3320.254492,"test":[47.46487561]},
{"learn":[47.50024149],"iteration":6,"passed_time":22.18813093,"remaining_time":3147.544859,"test":[47.41160647]},
{"learn":[47.44970427],"iteration":7,"passed_time":25.60708806,"remaining_time":3175.278919,"test":[47.36076824]},
{"learn":[47.40182327],"iteration":8,"passed_time":28.06855738,"remaining_time":3090.66004,"test":[47.31245356]},
{"learn":[47.3588954],"iteration":9,"passed_time":30.20289045,"remaining_time":2990.086155,"test":[47.26937393]},
{"learn":[47.32031835],"iteration":10,"passed_time":32.68617531,"remaining_time":2938.784308,"test":[47.23019307]},
{"learn":[47.28249967],"iteration":11,"passed_time":35.36193535,"remaining_time":2911.46601,"test":[47.19230053]},
{"learn":[47.24850556],"iteration":12,"passed_time":37.68971491,"remaining_time":2861.519124,"test":[47.1583025]},
{"learn":[47.21491666],"iteration":13,"passed_time":39.83851846,"remaining_time":2805.769943,"test":[47.12415435]},
{"learn":[47.18434671],"iteration":14,"passed_time":42.4752466,"remaining_time":2789.20786,"test":[47.0935098]},
{"learn":[47.15559951],"iteration":15,"passed_time":44.767906,"remaining_time":2753.226219,"test":[47.06433278]},
{"learn":[47.13017494],"iteration":16,"passed_time":47.51074649,"remaining_time":2747.239047,"test":[47.03903115]},
{"learn":[47.10543395],"iteration":17,"passed_time":50.5598035,"remaining_time":2758.318169,"test":[47.01392332]},
{"learn":[47.08304143],"iteration":18,"passed_time":52.72024785,"remaining_time":2722.029639,"test":[46.99124512]},
{"learn":[47.06073094],"iteration":19,"passed_time":55.52851877,"remaining_time":2720.89742,"test":[46.9686887]},
{"learn":[47.03959049],"iteration":20,"passed_time":57.72004422,"remaining_time":2690.85349,"test":[46.9474081]},
{"learn":[47.01890871],"iteration":21,"passed_time":60.2175381,"remaining_time":2676.943285,"test":[46.92647283]},
{"learn":[46.9998335],"iteration":22,"passed_time":63.3440776,"remaining_time":2690.746253,"test":[46.90722748]},
{"learn":[46.98233756],"iteration":23,"passed_time":66.48454196,"remaining_time":2703.704706,"test":[46.88976333]},
{"learn":[46.96301615],"iteration":24,"passed_time":68.96278505,"remaining_time":2689.548617,"test":[46.87033124]},
{"learn":[46.94665887],"iteration":25,"passed_time":71.78889762,"remaining_time":2689.322549,"test":[46.85413305]},
{"learn":[46.93033926],"iteration":26,"passed_time":74.2101506,"remaining_time":2674.313946,"test":[46.83789412]},
{"learn":[46.91462303],"iteration":27,"passed_time":76.97895903,"remaining_time":2672.269578,"test":[46.82191775]},
{"learn":[46.8996808],"iteration":28,"passed_time":80.05283475,"remaining_time":2680.389743,"test":[46.80669258]},
{"learn":[46.88560576],"iteration":29,"passed_time":82.1664947,"remaining_time":2656.716662,"test":[46.79245952]},
{"learn":[46.87233747],"iteration":30,"passed_time":84.95477595,"remaining_time":2655.521867,"test":[46.77930377]},
{"learn":[46.85798801],"iteration":31,"passed_time":86.98760379,"remaining_time":2631.375015,"test":[46.76481424]},
{"learn":[46.84588594],"iteration":32,"passed_time":89.52096886,"remaining_time":2623.235663,"test":[46.75266882]},
{"learn":[46.8340805],"iteration":33,"passed_time":91.90263598,"remaining_time":2611.116069,"test":[46.74093656]},
{"learn":[46.82271106],"iteration":34,"passed_time":95.31239085,"remaining_time":2627.898776,"test":[46.72926386]},
{"learn":[46.81170423],"iteration":35,"passed_time":97.27735976,"remaining_time":2604.871523,"test":[46.7181357]},
{"learn":[46.80090549],"iteration":36,"passed_time":100.2394637,"remaining_time":2608.93523,"test":[46.70702876]},
{"learn":[46.790513],"iteration":37,"passed_time":103.1804081,"remaining_time":2612.093488,"test":[46.69672399]},
{"learn":[46.78153246],"iteration":38,"passed_time":105.8903493,"remaining_time":2609.246813,"test":[46.68783242]},
{"learn":[46.77274741],"iteration":39,"passed_time":108.1068606,"remaining_time":2594.564655,"test":[46.67893166]},
{"learn":[46.76194449],"iteration":40,"passed_time":110.222142,"remaining_time":2578.122786,"test":[46.66788725]},
{"learn":[46.75283283],"iteration":41,"passed_time":112.8901113,"remaining_time":2574.969682,"test":[46.65877093]},
{"learn":[46.74279312],"iteration":42,"passed_time":115.5036424,"remaining_time":2570.627576,"test":[46.64866741]},
{"learn":[46.73352681],"iteration":43,"passed_time":117.7733786,"remaining_time":2558.894317,"test":[46.63924188]},
{"learn":[46.72453604],"iteration":44,"passed_time":119.9812945,"remaining_time":2546.269695,"test":[46.63020678]},
{"learn":[46.71542711],"iteration":45,"passed_time":123.0240329,"remaining_time":2551.411465,"test":[46.6210716]},
{"learn":[46.70750794],"iteration":46,"passed_time":126.4165666,"remaining_time":2563.297617,"test":[46.61315127]},
{"learn":[46.698492],"iteration":47,"passed_time":129.5008215,"remaining_time":2568.43296,"test":[46.60412477]},
{"learn":[46.68947075],"iteration":48,"passed_time":132.0980389,"remaining_time":2563.780306,"test":[46.59506825]},
{"learn":[46.68216765],"iteration":49,"passed_time":134.6821779,"remaining_time":2558.961379,"test":[46.5873579]},
{"learn":[46.6747207],"iteration":50,"passed_time":137.2485409,"remaining_time":2553.899319,"test":[46.57978815]},
{"learn":[46.66685892],"iteration":51,"passed_time":140.1336326,"remaining_time":2554.743917,"test":[46.57201922]},
{"learn":[46.66002342],"iteration":52,"passed_time":142.5492586,"remaining_time":2547.059394,"test":[46.5651264]},
{"learn":[46.65392325],"iteration":53,"passed_time":145.4281299,"remaining_time":2547.685387,"test":[46.55893824]},
{"learn":[46.64712933],"iteration":54,"passed_time":148.850556,"remaining_time":2557.523189,"test":[46.55210071]},
{"learn":[46.64091641],"iteration":55,"passed_time":151.8171718,"remaining_time":2559.203754,"test":[46.54610094]}
]}